blipper/__init__.py
blipper/blipper.py
blipper/config.py
blipper-0.1.8.dist-info/METADATA
blipper-0.1.8.dist-info/WHEEL
blipper-0.1.8.dist-info/top_level.txt
blipper-0.1.8.dist-info/RECORD
