Metadata-Version: 2.4
Name: blipper
Version: 0.1.8
Summary: Blipper is an AI application that empowers you to access large language model capabilities through a high-level interface. Blipper provides a lot of functions each with a task of their own. We call them Blips.
Requires-Python: >=3.10
Requires-Dist: requests>=2.32.3
